CargoEntityExtractor/CargoEntityExtractor.py
CargoEntityExtractor/Load_Cargo_Model.py
CargoEntityExtractor/TextCleaner.py
CargoEntityExtractor/WordReplacements.py
CargoEntityExtractor/__init__.py
EntityExtractor/EntityExtractor.py
EntityExtractor/Load_First_Model.py
EntityExtractor/Load_Second_Model.py
EntityExtractor/Load_Third_Model.py
EntityExtractor/__init__.py
EntityExtractor-0.6.6.3.dist-info/METADATA
EntityExtractor-0.6.6.3.dist-info/WHEEL
EntityExtractor-0.6.6.3.dist-info/top_level.txt
EntityExtractor-0.6.6.3.dist-info/RECORD
