Metadata-Version: 2.1
Name: EntityExtractor
Version: 0.6.6.3
Summary: Extract specific entities from a text. Give Base64 and get a JSON formatted output data.
Home-page: UNKNOWN
Author: Ankit Mor
License: UNKNOWN
Platform: UNKNOWN
Requires-Dist: nltk >=3.8.1
Requires-Dist: requests
Requires-Dist: BeautifulSoup4
Requires-Dist: spacy >=3.7.2
Requires-Dist: spacy-transformers
